Metadata-Version: 2.1
Name: tinynet
Version: 0.1.2
Summary: A tiny neural network library
Home-page: https://github.com/giuse/tinynet
Author: Giuseppe Cuccu
Author-email: giuseppe.cuccu@gmail.com
License: MIT
Download-URL: https://github.com/giuse/tinynet/archive/0.1.2.tar.gz
Project-URL: Bug Reports, https://github.com/giuse/tinynet/issues
Project-URL: Source, https://github.com/giuse/tinynet/
Keywords: neuralnetwork machinelearning
Platform: UNKNOWN
Classifier: Development Status :: 4 - Beta
Classifier: Intended Audience :: Developers
Classifier: Topic :: Software Development :: Build Tools
Classifier: License :: OSI Approved :: MIT License
Classifier: Programming Language :: Python :: 3 :: Only
Classifier: Programming Language :: Python :: 3.6
Classifier: Programming Language :: Python :: 3.7
Classifier: Programming Language :: Python :: 3.8
Classifier: Topic :: Scientific/Engineering :: Artificial Intelligence
Requires-Python: >=3.6, <4
